eth_rpc_client/__init__.py
eth_rpc_client/client.py
ethereum_rpc_client-0.4.4.dist-info/DESCRIPTION.rst
ethereum_rpc_client-0.4.4.dist-info/METADATA
ethereum_rpc_client-0.4.4.dist-info/metadata.json
ethereum_rpc_client-0.4.4.dist-info/RECORD
ethereum_rpc_client-0.4.4.dist-info/top_level.txt
ethereum_rpc_client-0.4.4.dist-info/WHEEL
