Metadata-Version: 2.0
Name: ethereum-rpc-client
Version: 0.4.4
Summary: Ethereum JSON RPC Client
Home-page: https://github.com/pipermerriam/ethereum-rpc-client
Author: Piper Merriam
Author-email: pipermerriam@gmail.com
License: MIT
Keywords: ethereum json json-rpc
Platform: UNKNOWN
Classifier: Development Status :: 2 - Pre-Alpha
Classifier: Intended Audience :: Developers
Classifier: License :: OSI Approved :: BSD License
Classifier: Natural Language :: English
Classifier: Programming Language :: Python :: 2
Classifier: Programming Language :: Python :: 2.7
Classifier: Programming Language :: Python :: 3
Classifier: Programming Language :: Python :: 3.3
Classifier: Programming Language :: Python :: 3.4
Requires-Dist: requests (>=2.7.0)
Requires-Dist: ethereum-client-utils (>=0.3.0)
